PyFiware-0.71.dist-info/DESCRIPTION.rst
PyFiware-0.71.dist-info/METADATA
PyFiware-0.71.dist-info/RECORD
PyFiware-0.71.dist-info/WHEEL
PyFiware-0.71.dist-info/metadata.json
PyFiware-0.71.dist-info/top_level.txt
pyfiware/__init__.py
pyfiware/history.py
pyfiware/oauth.py
