Metadata-Version: 2.0
Name: PyFiware
Version: 0.71
Summary: Python library to access Fiware REST API v2
Home-page: https://github.com/josubg/pyfiware
Author: Josu Bermudez
Author-email: josu.bermudez@deusto.es
License: UNKNOWN
Platform: UNKNOWN
Classifier: Development Status :: 3 - Alpha
Classifier: Intended Audience :: Developers
Classifier: Programming Language :: Python :: 3
Classifier: Topic :: Software Development :: Libraries
Classifier: Topic :: Software Development :: Libraries :: Python Modules
Requires-Dist: urllib3
